tawizard/__init__.py
tawizard/__main__.py
tawizard/core.py
tawizard/custom.py
tawizard/candles/__init__.py
tawizard/candles/cdl_doji.py
tawizard/candles/cdl_inside.py
tawizard/candles/cdl_pattern.py
tawizard/candles/cdl_z.py
tawizard/candles/ha.py
tawizard/cycles/__init__.py
tawizard/cycles/ebsw.py
tawizard/momentum/__init__.py
tawizard/momentum/ao.py
tawizard/momentum/apo.py
tawizard/momentum/bias.py
tawizard/momentum/bop.py
tawizard/momentum/brar.py
tawizard/momentum/cci.py
tawizard/momentum/cfo.py
tawizard/momentum/cg.py
tawizard/momentum/cmo.py
tawizard/momentum/coppock.py
tawizard/momentum/cti.py
tawizard/momentum/dm.py
tawizard/momentum/er.py
tawizard/momentum/eri.py
tawizard/momentum/fisher.py
tawizard/momentum/inertia.py
tawizard/momentum/kdj.py
tawizard/momentum/kst.py
tawizard/momentum/macd.py
tawizard/momentum/mom.py
tawizard/momentum/pgo.py
tawizard/momentum/ppo.py
tawizard/momentum/psl.py
tawizard/momentum/pvo.py
tawizard/momentum/qqe.py
tawizard/momentum/roc.py
tawizard/momentum/rsi.py
tawizard/momentum/rsx.py
tawizard/momentum/rvgi.py
tawizard/momentum/slope.py
tawizard/momentum/smi.py
tawizard/momentum/squeeze.py
tawizard/momentum/squeeze_pro.py
tawizard/momentum/stc.py
tawizard/momentum/stoch.py
tawizard/momentum/stochrsi.py
tawizard/momentum/td_seq.py
tawizard/momentum/trix.py
tawizard/momentum/tsi.py
tawizard/momentum/uo.py
tawizard/momentum/willr.py
tawizard/overlap/__init__.py
tawizard/overlap/alma.py
tawizard/overlap/dema.py
tawizard/overlap/ema.py
tawizard/overlap/fwma.py
tawizard/overlap/hilo.py
tawizard/overlap/hl2.py
tawizard/overlap/hlc3.py
tawizard/overlap/hma.py
tawizard/overlap/hwma.py
tawizard/overlap/ichimoku.py
tawizard/overlap/jma.py
tawizard/overlap/kama.py
tawizard/overlap/linreg.py
tawizard/overlap/ma.py
tawizard/overlap/mcgd.py
tawizard/overlap/midpoint.py
tawizard/overlap/midprice.py
tawizard/overlap/ohlc4.py
tawizard/overlap/pwma.py
tawizard/overlap/rma.py
tawizard/overlap/sinwma.py
tawizard/overlap/sma.py
tawizard-1.0.5.dist-info/LICENSE.txt
tawizard-1.0.5.dist-info/METADATA
tawizard-1.0.5.dist-info/WHEEL
tawizard-1.0.5.dist-info/top_level.txt
tawizard-1.0.5.dist-info/RECORD
